ledger_analytics/__about__.py
ledger_analytics/__init__.py
ledger_analytics/api.py
ledger_analytics/autofit.py
ledger_analytics/cashflow.py
ledger_analytics/config.py
ledger_analytics/console.py
ledger_analytics/development.py
ledger_analytics/forecast.py
ledger_analytics/interface.py
ledger_analytics/model.py
ledger_analytics/requester.py
ledger_analytics/tail.py
ledger_analytics/triangle.py
ledger_analytics-0.0.30.dist-info/METADATA
ledger_analytics-0.0.30.dist-info/WHEEL
ledger_analytics-0.0.30.dist-info/licenses/LICENSE.txt
ledger_analytics-0.0.30.dist-info/RECORD
